Digital-Circuit-Design/MP3/Clock.v
`timescale 100ms/10ms
module BCD_counter(count,TC,clr_, enb, clk) ;
output reg [3:0] count ;
output reg TC ;
input clr_, enb, clk ;

always @ (*)
	if(enb && count >= 9)
		TC = 1;
	else
		TC = 0;
	
always @ (posedge clk or negedge clr_) // combinational+sequential
	if (~clr_)
		count = 0 ;
	else if (enb)
		if (TC)
			count = 0;
		else
			count = count + 1;
endmodule

module Hex_counter(count,TC,clr_, enb, clk) ;
output reg [2:0] count ;
output reg TC ;
input clr_, enb, clk ;

always @ (*)
	if(enb && count >= 5)
		TC = 1;
	else
		TC = 0;
		
always @ (posedge clk or negedge clr_) // combinational+sequential
	if (~clr_)
		count = 0 ;
	else if (enb)
		if (TC)
			count = 0;
		else
			count = count + 1 ;
endmodule

module H1_counter(count,TC,clr_, enb, clk) ;
output reg [1:0] count ;
output reg TC ;
input clr_, enb, clk ;

always @ (*)
	if(enb && count >= 2)
		TC = 1;
	else
		TC = 0;
		
always @ (posedge clk or negedge clr_) // combinational+sequential
	if (~clr_)
		count = 0 ;
	else if (enb)
		if (TC)
			count = 0;
		else
			count = count + 1 ;
endmodule

module H0_counter(count,TC,clr_, enb, clk, h11) ;
output reg [3:0] count ;
output reg TC ;
input clr_, enb, clk, h11 ;

always @ (*)
	if(enb && count >= (h11 ? 3 : 9))
		TC = 1;
	else
		TC = 0;
	
always @ (posedge clk or negedge clr_) // combinational+sequential
	if (~clr_)
		count = 0 ;
	else if (enb)
		if (TC)
			count = 0;
		else
			count = count + 1;
endmodule


module Testfixture ;
wire Vdd = 1'b1;
reg clk, clr_;
wire [3:0] m0 ;
wire [2:0] m1 ;
wire [3:0] h0 ;
wire [1:0] h1 ;

BCD_counter M0 (m0,m0_tc,clr_, Vdd, clk) ;
Hex_counter M1 (m1,m1_tc,clr_, m0_tc, clk) ;
H1_counter H1 (h1,h1_tc,clr_, h0_tc, clk) ;
H0_counter H0 (h0,h0_tc,clr_, m1_tc, clk, h1[1]) ;


//Stimulus
initial
begin
	clk = 1'b0 ;
	repeat(4800)
		#5 clk = ~clk ;
	$finish ;
end
	
initial
begin
  clr_ = 0;
  #6  clr_ = 1'b1;  
end

initial
begin
$dumpfile("Clock.vcd");
$dumpvars;
end

endmodule

Digital-Circuit-Design/MP3/Clock.vcd
$date
	Tue Jun  5 19:53:48 2018
$end
$version
	Icarus Verilog
$end
$timescale
	10ms
$end
$scope module Testfixture $end
$var wire 1 ! Vdd $end
$var wire 1 " m1_tc $end
$var wire 3 # m1 [2:0] $end
$var wire 1 $ m0_tc $end
$var wire 4 % m0 [3:0] $end
$var wire 1 & h1_tc $end
$var wire 2 ' h1 [1:0] $end
$var wire 1 ( h0_tc $end
$var wire 4 ) h0 [3:0] $end
$var reg 1 * clk $end
$var reg 1 + clr_ $end
$scope module H0 $end
$var wire 1 * clk $end
$var wire 1 + clr_ $end
$var wire 1 , h11 $end
$var wire 1 " enb $end
$var reg 1 ( TC $end
$var reg 4 - count [3:0] $end
$upscope $end
$scope module H1 $end
$var wire 1 * clk $end
$var wire 1 + clr_ $end
$var wire 1 ( enb $end
$var reg 1 & TC $end
$var reg 2 . count [1:0] $end
$upscope $end
$scope module M0 $end
$var wire 1 * clk $end
$var wire 1 + clr_ $end
$var wire 1 ! enb $end
$var reg 1 $ TC $end
$var reg 4 / count [3:0] $end
$upscope $end
$scope module M1 $end
$var wire 1 * clk $end
$var wire 1 + clr_ $end
$var wire 1 $ enb $end
$var reg 1 " TC $end
$var reg 3 0 count [2:0] $end
$upscope $end
$upscope $end
$enddefinitions $end
#0
$dumpvars
b0 0
b0 /
b0 .
b0 -
0,
0+
0*
b0 )
0(
b0 '
0&
b0 %
0$
b0 #
0"
1!
$end
#50
1*
#60
1+
#100
0*
#150
b1 %
b1 /
1*
#200
0*
#250
b10 %
b10 /
1*
#300
0*
#350
b11 %
b11 /
1*
#400
0*
#450
b100 %
b100 /
1*
#500
0*
#550
b101 %
b101 /
1*
#600
0*
#650
b110 %
b110 /
1*
#700
0*
#750
b111 %
b111 /
1*
#800
0*
#850
b1000 %
b1000 /
1*
#900
0*
#950
1$
b1001 %
b1001 /
1*
#1000
0*
#1050
0$
b1 #
b1 0
b0 %
b0 /
1*
#1100
0*
#1150
b1 %
b1 /
1*
#1200
0*
#1250
b10 %
b10 /
1*
#1300
0*
#1350
b11 %
b11 /
1*
#1400
0*
#1450
b100 %
b100 /
1*
#1500
0*
#1550
b101 %
b101 /
1*
#1600
0*
#1650
b110 %
b110 /
1*
#1700
0*
#1750
b111 %
b111 /
1*
#1800
0*
#1850
b1000 %
b1000 /
1*
#1900
0*
#1950
1$
b1001 %
b1001 /
1*
#2000
0*
#2050
0$
b10 #
b10 0
b0 %
b0 /
1*
#2100
0*
#2150
b1 %
b1 /
1*
#2200
0*
#2250
b10 %
b10 /
1*
#2300
0*
#2350
b11 %
b11 /
1*
#2400
0*
#2450
b100 %
b100 /
1*
#2500
0*
#2550
b101 %
b101 /
1*
#2600
0*
#2650
b110 %
b110 /
1*
#2700
0*
#2750
b111 %
b111 /
1*
#2800
0*
#2850
b1000 %
b1000 /
1*
#2900
0*
#2950
1$
b1001 %
b1001 /
1*
#3000
0*
#3050
0$
b11 #
b11 0
b0 %
b0 /
1*
#3100
0*
#3150
b1 %
b1 /
1*
#3200
0*
#3250
b10 %
b10 /
1*
#3300
0*
#3350
b11 %
b11 /
1*
#3400
0*
#3450
b100 %
b100 /
1*
#3500
0*
#3550
b101 %
b101 /
1*
#3600
0*
#3650
b110 %
b110 /
1*
#3700
0*
#3750
b111 %
b111 /
1*
#3800
0*
#3850
b1000 %
b1000 /
1*
#3900
0*
#3950
1$
b1001 %
b1001 /
1*
#4000
0*
#4050
0$
b100 #
b100 0
b0 %
b0 /
1*
#4100
0*
#4150
b1 %
b1 /
1*
#4200
0*
#4250
b10 %
b10 /
1*
#4300
0*
#4350
b11 %
b11 /
1*
#4400
0*
#4450
b100 %
b100 /
1*
#4500
0*
#4550
b101 %
b101 /
1*
#4600
0*
#4650
b110 %
b110 /
1*
#4700
0*
#4750
b111 %
b111 /
1*
#4800
0*
#4850
b1000 %
b1000 /
1*
#4900
0*
#4950
1$
b1001 %
b1001 /
1*
#5000
0*
#5050
0$
b101 #
b101 0
b0 %
b0 /
1*
#5100
0*
#5150
b1 %
b1 /
1*
#5200
0*
#5250
b10 %
b10 /
1*
#5300
0*
#5350
b11 %
b11 /
1*
#5400
0*
#5450
b100 %
b100 /
1*
#5500
0*
#5550
b101 %
b101 /
1*
#5600
0*
#5650
b110 %
b110 /
1*
#5700
0*
#5750
b111 %
b111 /
1*
#5800
0*
#5850
b1000 %
b1000 /
1*
#5900
0*
#5950
1"
1$
b1001 %
b1001 /
1*
#6000
0*
#6050
0"
0$
b1 )
b1 -
b0 #
b0 0
b0 %
b0 /
1*
#6100
0*
#6150
b1 %
b1 /
1*
#6200
0*
#6250
b10 %
b10 /
1*
#6300
0*
#6350
b11 %
b11 /
1*
#6400
0*
#6450
b100 %
b100 /
1*
#6500
0*
#6550
b101 %
b101 /
1*
#6600
0*
#6650
b110 %
b110 /
1*
#6700
0*
#6750
b111 %
b111 /
1*
#6800
0*
#6850
b1000 %
b1000 /
1*
#6900
0*
#6950
1$
b1001 %
b1001 /
1*
#7000
0*
#7050
0$
b1 #
b1 0
b0 %
b0 /
1*
#7100
0*
#7150
b1 %
b1 /
1*
#7200
0*
#7250
b10 %
b10 /
1*
#7300
0*
#7350
b11 %
b11 /
1*
#7400
0*
#7450
b100 %
b100 /
1*
#7500
0*
#7550
b101 %
b101 /
1*
#7600
0*
#7650
b110 %
b110 /
1*
#7700
0*
#7750
b111 %
b111 /
1*
#7800
0*
#7850
b1000 %
b1000 /
1*
#7900
0*
#7950
1$
b1001 %
b1001 /
1*
#8000
0*
#8050
0$
b10 #
b10 0
b0 %
b0 /
1*
#8100
0*
#8150
b1 %
b1 /
1*
#8200
0*
#8250
b10 %
b10 /
1*
#8300
0*
#8350
b11 %
b11 /
1*
#8400
0*
#8450
b100 %
b100 /
1*
#8500
0*
#8550
b101 %
b101 /
1*
#8600
0*
#8650
b110 %
b110 /
1*
#8700
0*
#8750
b111 %
b111 /
1*
#8800
0*
#8850
b1000 %
b1000 /
1*
#8900
0*
#8950
1$
b1001 %
b1001 /
1*
#9000
0*
#9050
0$
b11 #
b11 0
b0 %
b0 /
1*
#9100
0*
#9150
b1 %
b1 /
1*
#9200
0*
#9250
b10 %
b10 /
1*
#9300
0*
#9350
b11 %
b11 /
1*
#9400
0*
#9450
b100 %
b100 /
1*
#9500
0*
#9550
b101 %
b101 /
1*
#9600
0*
#9650
b110 %
b110 /
1*
#9700
0*
#9750
b111 %
b111 /
1*
#9800
0*
#9850
b1000 %
b1000 /
1*
#9900
0*
#9950
1$
b1001 %
b1001 /
1*
#10000
0*
#10050
0$
b100 #
b100 0
b0 %
b0 /
1*
#10100
0*
#10150
b1 %
b1 /
1*
#10200
0*
#10250
b10 %
b10 /
1*
#10300
0*
#10350
b11 %
b11 /
1*
#10400
0*
#10450
b100 %
b100 /
1*
#10500
0*
#10550
b101 %
b101 /
1*
#10600
0*
#10650
b110 %
b110 /
1*
#10700
0*
#10750
b111 %
b111 /
1*
#10800
0*
#10850
b1000 %
b1000 /
1*
#10900
0*
#10950
1$
b1001 %
b1001 /
1*
#11000
0*
#11050
0$
b101 #
b101 0
b0 %
b0 /
1*
#11100
0*
#11150
b1 %
b1 /
1*
#11200
0*
#11250
b10 %
b10 /
1*
#11300
0*
#11350
b11 %
b11 /
1*
#11400
0*
#11450
b100 %
b100 /
1*
#11500
0*
#11550
b101 %
b101 /
1*
#11600
0*
#11650
b110 %
b110 /
1*
#11700
0*
#11750
b111 %
b111 /
1*
#11800
0*
#11850
b1000 %
b1000 /
1*
#11900
0*
#11950
1"
1$
b1001 %
b1001 /
1*
#12000
0*
#12050
0"
0$
b10 )
b10 -
b0 #
b0 0
b0 %
b0 /
1*
#12100
0*
#12150
b1 %
b1 /
1*
#12200
0*
#12250
b10 %
b10 /
1*
#12300
0*
#12350
b11 %
b11 /
1*
#12400
0*
#12450
b100 %
b100 /
1*
#12500
0*
#12550
b101 %
b101 /
1*
#12600
0*
#12650
b110 %
b110 /
1*
#12700
0*
#12750
b111 %
b111 /
1*
#12800
0*
#12850
b1000 %
b1000 /
1*
#12900
0*
#12950
1$
b1001 %
b1001 /
1*
#13000
0*
#13050
0$
b1 #
b1 0
b0 %
b0 /
1*
#13100
0*
#13150
b1 %
b1 /
1*
#13200
0*
#13250
b10 %
b10 /
1*
#13300
0*
#13350
b11 %
b11 /
1*
#13400
0*
#13450
b100 %
b100 /
1*
#13500
0*
#13550
b101 %
b101 /
1*
#13600
0*
#13650
b110 %
b110 /
1*
#13700
0*
#13750
b111 %
b111 /
1*
#13800
0*
#13850
b1000 %
b1000 /
1*
#13900
0*
#13950
1$
b1001 %
b1001 /
1*
#14000
0*
#14050
0$
b10 #
b10 0
b0 %
b0 /
1*
#14100
0*
#14150
b1 %
b1 /
1*
#14200
0*
#14250
b10 %
b10 /
1*
#14300
0*
#14350
b11 %
b11 /
1*
#14400
0*
#14450
b100 %
b100 /
1*
#14500
0*
#14550
b101 %
b101 /
1*
#14600
0*
#14650
b110 %
b110 /
1*
#14700
0*
#14750
b111 %
b111 /
1*
#14800
0*
#14850
b1000 %
b1000 /
1*
#14900
0*
#14950
1$
b1001 %
b1001 /
1*
#15000
0*
#15050
0$
b11 #
b11 0
b0 %
b0 /
1*
#15100
0*
#15150
b1 %
b1 /
1*
#15200
0*
#15250
b10 %
b10 /
1*
#15300
0*
#15350
b11 %
b11 /
1*
#15400
0*
#15450
b100 %
b100 /
1*
#15500
0*
#15550
b101 %
b101 /
1*
#15600
0*
#15650
b110 %
b110 /
1*
#15700
0*
#15750
b111 %
b111 /
1*
#15800
0*
#15850
b1000 %
b1000 /
1*
#15900
0*
#15950
1$
b1001 %
b1001 /
1*
#16000
0*
#16050
0$
b100 #
b100 0
b0 %
b0 /
1*
#16100
0*
#16150
b1 %
b1 /
1*
#16200
0*
#16250
b10 %
b10 /
1*
#16300
0*
#16350
b11 %
b11 /
1*
#16400
0*
#16450
b100 %
b100 /
1*
#16500
0*
#16550
b101 %
b101 /
1*
#16600
0*
#16650
b110 %
b110 /
1*
#16700
0*
#16750
b111 %
b111 /
1*
#16800
0*
#16850
b1000 %
b1000 /
1*
#16900
0*
#16950
1$
b1001 %
b1001 /
1*
#17000
0*
#17050
0$
b101 #
b101 0
b0 %
b0 /
1*
#17100
0*
#17150
b1 %
b1 /
1*
#17200
0*
#17250
b10 %
b10 /
1*
#17300
0*
#17350
b11 %
b11 /
1*
#17400
0*
#17450
b100 %
b100 /
1*
#17500
0*
#17550
b101 %
b101 /
1*
#17600
0*
#17650
b110 %
b110 /
1*
#17700
0*
#17750
b111 %
b111 /
1*
#17800
0*
#17850
b1000 %
b1000 /
1*
#17900
0*
#17950
1"
1$
b1001 %
b1001 /
1*
#18000
0*
#18050
0"
0$
b11 )
b11 -
b0 #
b0 0
b0 %
b0 /
1*
#18100
0*
#18150
b1 %
b1 /
1*
#18200
0*
#18250
b10 %
b10 /
1*
#18300
0*
#18350
b11 %
b11 /
1*
#18400
0*
#18450
b100 %
b100 /
1*
#18500
0*
#18550
b101 %
b101 /
1*
#18600
0*
#18650
b110 %
b110 /
1*
#18700
0*
#18750
b111 %
b111 /
1*
#18800
0*
#18850
b1000 %
b1000 /
1*
#18900
0*
#18950
1$
b1001 %
b1001 /
1*
#19000
0*
#19050
0$
b1 #
b1 0
b0 %
b0 /
1*
#19100
0*
#19150
b1 %
b1 /
1*
#19200
0*
#19250
b10 %
b10 /
1*
#19300
0*
#19350
b11 %
b11 /
1*
#19400
0*
#19450
b100 %
b100 /
1*
#19500
0*
#19550
b101 %
b101 /
1*
#19600
0*
#19650
b110 %
b110 /
1*
#19700
0*
#19750
b111 %
b111 /
1*
#19800
0*
#19850
b1000 %
b1000 /
1*
#19900
0*
#19950
1$
b1001 %
b1001 /
1*
#20000
0*
#20050
0$
b10 #
b10 0
b0 %
b0 /
1*
#20100
0*
#20150
b1 %
b1 /
1*
#20200
0*
#20250
b10 %
b10 /
1*
#20300
0*
#20350
b11 %
b11 /
1*
#20400
0*
#20450
b100 %
b100 /
1*
#20500
0*
#20550
b101 %
b101 /
1*
#20600
0*
#20650
b110 %
b110 /
1*
#20700
0*
#20750
b111 %
b111 /
1*
#20800
0*
#20850
b1000 %
b1000 /
1*
#20900
0*
#20950
1$
b1001 %
b1001 /
1*
#21000
0*
#21050
0$
b11 #
b11 0
b0 %
b0 /
1*
#21100
0*
#21150
b1 %
b1 /
1*
#21200
0*
#21250
b10 %
b10 /
1*
#21300
0*
#21350
b11 %
b11 /
1*
#21400
0*
#21450
b100 %
b100 /
1*
#21500
0*
#21550
b101 %
b101 /
1*
#21600
0*
#21650
b110 %
b110 /
1*
#21700
0*
#21750
b111 %
b111 /
1*
#21800
0*
#21850
b1000 %
b1000 /
1*
#21900
0*
#21950
1$
b1001 %
b1001 /
1*
#22000
0*
#22050
0$
b100 #
b100 0
b0 %
b0 /
1*
#22100
0*
#22150
b1 %
b1 /
1*
#22200
0*
#22250
b10 %
b10 /
1*
#22300
0*
#22350
b11 %
b11 /
1*
#22400
0*
#22450
b100 %
b100 /
1*
#22500
0*
#22550
b101 %
b101 /
1*
#22600
0*
#22650
b110 %
b110 /
1*
#22700
0*
#22750
b111 %
b111 /
1*
#22800
0*
#22850
b1000 %
b1000 /
1*
#22900
0*
#22950
1$
b1001 %
b1001 /
1*
#23000
0*
#23050
0$
b101 #
b101 0
b0 %
b0 /
1*
#23100
0*
#23150
b1 %
b1 /
1*
#23200
0*
#23250
b10 %
b10 /
1*
#23300
0*
#23350
b11 %
b11 /
1*
#23400
0*
#23450
b100 %
b100 /
1*
#23500
0*
#23550
b101 %
b101 /
1*
#23600
0*
#23650
b110 %
b110 /
1*
#23700
0*
#23750
b111 %
b111 /
1*
#23800
0*
#23850
b1000 %
b1000 /
1*
#23900
0*
#23950
1"
1$
b1001 %
b1001 /
1*
#24000
0*
#24050
0"
0$
b100 )
b100 -
b0 #
b0 0
b0 %
b0 /
1*
#24100
0*
#24150
b1 %
b1 /
1*
#24200
0*
#24250
b10 %
b10 /
1*
#24300
0*
#24350
b11 %
b11 /
1*
#24400
0*
#24450
b100 %
b100 /
1*
#24500
0*
#24550
b101 %
b101 /
1*
#24600
0*
#24650
b110 %
b110 /
1*
#24700
0*
#24750
b111 %
b111 /
1*
#24800
0*
#24850
b1000 %
b1000 /
1*
#24900
0*
#24950
1$
b1001 %
b1001 /
1*
#25000
0*
#25050
0$
b1 #
b1 0
b0 %
b0 /
1*
#25100
0*
#25150
b1 %
b1 /
1*
#25200
0*
#25250
b10 %
b10 /
1*
#25300
0*
#25350
b11 %
b11 /
1*
#25400
0*
#25450
b100 %
b100 /
1*
#25500
0*
#25550
b101 %
b101 /
1*
#25600
0*
#25650
b110 %
b110 /
1*
#25700
0*
#25750
b111 %
b111 /
1*
#25800
0*
#25850
b1000 %
b1000 /
1*
#25900
0*
#25950
1$
b1001 %
b1001 /
1*
#26000
0*
#26050
0$
b10 #
b10 0
b0 %
b0 /
1*
#26100
0*
#26150
b1 %
b1 /
1*
#26200
0*
#26250
b10 %
b10 /
1*
#26300
0*
#26350
b11 %
b11 /
1*
#26400
0*
#26450
b100 %
b100 /
1*
#26500
0*
#26550
b101 %
b101 /
1*
#26600
0*
#26650
b110 %
b110 /
1*
#26700
0*
#26750
b111 %
b111 /
1*
#26800
0*
#26850
b1000 %
b1000 /
1*
#26900
0*
#26950
1$
b1001 %
b1001 /
1*
#27000
0*
#27050
0$
b11 #
b11 0
b0 %
b0 /
1*
#27100
0*
#27150
b1 %
b1 /
1*
#27200
0*
#27250
b10 %
b10 /
1*
#27300
0*
#27350
b11 %
b11 /
1*
#27400
0*
#27450
b100 %
b100 /
1*
#27500
0*
#27550
b101 %
b101 /
1*
#27600
0*
#27650
b110 %
b110 /
1*
#27700
0*
#27750
b111 %
b111 /
1*
#27800
0*
#27850
b1000 %
b1000 /
1*
#27900
0*
#27950
1$
b1001 %
b1001 /
1*
#28000
0*
#28050
0$
b100 #
b100 0
b0 %
b0 /
1*
#28100
0*
#28150
b1 %
b1 /
1*
#28200
0*
#28250
b10 %
b10 /
1*
#28300
0*
#28350
b11 %
b11 /
1*
#28400
0*
#28450
b100 %
b100 /
1*
#28500
0*
#28550
b101 %
b101 /
1*
#28600
0*
#28650
b110 %
b110 /
1*
#28700
0*
#28750
b111 %
b111 /
1*
#28800
0*
#28850
b1000 %
b1000 /
1*
#28900
0*
#28950
1$
b1001 %
b1001 /
1*
#29000
0*
#29050
0$
b101 #
b101 0
b0 %
b0 /
1*
#29100
0*
#29150
b1 %
b1 /
1*
#29200
0*
#29250
b10 %
b10 /
1*
#29300
0*
#29350
b11 %
b11 /
1*
#29400
0*
#29450
b100 %
b100 /
1*
#29500
0*
#29550
b101 %
b101 /
1*
#29600
0*
#29650
b110 %
b110 /
1*
#29700
0*
#29750
b111 %
b111 /
1*
#29800
0*
#29850
b1000 %
b1000 /
1*
#29900
0*
#29950
1"
1$
b1001 %
b1001 /
1*
#30000
0*
#30050
0"
0$
b101 )
b101 -
b0 #
b0 0
b0 %
b0 /
1*
#30100
0*
#30150
b1 %
b1 /
1*
#30200
0*
#30250
b10 %
b10 /
1*
#30300
0*
#30350
b11 %
b11 /
1*
#30400
0*
#30450
b100 %
b100 /
1*
#30500
0*
#30550
b101 %
b101 /
1*
#30600
0*
#30650
b110 %
b110 /
1*
#30700
0*
#30750
b111 %
b111 /
1*
#30800
0*
#30850
b1000 %
b1000 /
1*
#30900
0*
#30950
1$
b1001 %
b1001 /
1*
#31000
0*
#31050
0$
b1 #
b1 0
b0 %
b0 /
1*
#31100
0*
#31150
b1 %
b1 /
1*
#31200
0*
#31250
b10 %
b10 /
1*
#31300
0*
#31350
b11 %
b11 /
1*
#31400
0*
#31450
b100 %
b100 /
1*
#31500
0*
#31550
b101 %
b101 /
1*
#31600
0*
#31650
b110 %
b110 /
1*
#31700
0*
#31750
b111 %
b111 /
1*
#31800
0*
#31850
b1000 %
b1000 /
1*
#31900
0*
#31950
1$
b1001 %
b1001 /
1*
#32000
0*
#32050
0$
b10 #
b10 0
b0 %
b0 /
1*
#32100
0*
#32150
b1 %
b1 /
1*
#32200
0*
#32250
b10 %
b10 /
1*
#32300
0*
#32350
b11 %
b11 /
1*
#32400
0*
#32450
b100 %
b100 /
1*
#32500
0*
#32550
b101 %
b101 /
1*
#32600
0*
#32650
b110 %
b110 /
1*
#32700
0*
#32750
b111 %
b111 /
1*
#32800
0*
#32850
b1000 %
b1000 /
1*
#32900
0*
#32950
1$
b1001 %
b1001 /
1*
#33000
0*
#33050
0$
b11 #
b11 0
b0 %
b0 /
1*
#33100
0*
#33150
b1 %
b1 /
1*
#33200
0*
#33250
b10 %
b10 /
1*
#33300
0*
#33350
b11 %
b11 /
1*
#33400
0*
#33450
b100 %
b100 /
1*
#33500
0*
#33550
b101 %
b101 /
1*
#33600
0*
#33650
b110 %
b110 /
1*
#33700
0*
#33750
b111 %
b111 /
1*
#33800
0*
#33850
b1000 %
b1000 /
1*
#33900
0*
#33950
1$
b1001 %
b1001 /
1*
#34000
0*
#34050
0$
b100 #
b100 0
b0 %
b0 /
1*
#34100
0*
#34150
b1 %
b1 /
1*
#34200
0*
#34250
b10 %
b10 /
1*
#34300
0*
#34350
b11 %
b11 /
1*
#34400
0*
#34450
b100 %
b100 /
1*
#34500
0*
#34550
b101 %
b101 /
1*
#34600
0*
#34650
b110 %
b110 /
1*
#34700
0*
#34750
b111 %
b111 /
1*
#34800
0*
#34850
b1000 %
b1000 /
1*
#34900
0*
#34950
1$
b1001 %
b1001 /
1*
#35000
0*
#35050
0$
b101 #
b101 0
b0 %
b0 /
1*
#35100
0*
#35150
b1 %
b1 /
1*
#35200
0*
#35250
b10 %
b10 /
1*
#35300
0*
#35350
b11 %
b11 /
1*
#35400
0*
#35450
b100 %
b100 /
1*
#35500
0*
#35550
b101 %
b101 /
1*
#35600
0*
#35650
b110 %
b110 /
1*
#35700
0*
#35750
b111 %
b111 /
1*
#35800
0*
#35850
b1000 %
b1000 /
1*
#35900
0*
#35950
1"
1$
b1001 %
b1001 /
1*
#36000
0*
#36050
0"
0$
b110 )
b110 -
b0 #
b0 0
b0 %
b0 /
1*
#36100
0*
#36150
b1 %
b1 /
1*
#36200
0*
#36250
b10 %
b10 /
1*
#36300
0*
#36350
b11 %
b11 /
1*
#36400
0*
#36450
b100 %
b100 /
1*
#36500
0*
#36550
b101 %
b101 /
1*
#36600
0*
#36650
b110 %
b110 /
1*
#36700
0*
#36750
b111 %
b111 /
1*
#36800
0*
#36850
b1000 %
b1000 /
1*
#36900
0*
#36950
1$
b1001 %
b1001 /
1*
#37000
0*
#37050
0$
b1 #
b1 0
b0 %
b0 /
1*
#37100
0*
#37150
b1 %
b1 /
1*
#37200
0*
#37250
b10 %
b10 /
1*
#37300
0*
#37350
b11 %
b11 /
1*
#37400
0*
#37450
b100 %
b100 /
1*
#37500
0*
#37550
b101 %
b101 /
1*
#37600
0*
#37650
b110 %
b110 /
1*
#37700
0*
#37750
b111 %
b111 /
1*
#37800
0*
#37850
b1000 %
b1000 /
1*
#37900
0*
#37950
1$
b1001 %
b1001 /
1*
#38000
0*
#38050
0$
b10 #
b10 0
b0 %
b0 /
1*
#38100
0*
#38150
b1 %
b1 /
1*
#38200
0*
#38250
b10 %
b10 /
1*
#38300
0*
#38350
b11 %
b11 /
1*
#38400
0*
#38450
b100 %
b100 /
1*
#38500
0*
#38550
b101 %
b101 /
1*
#38600
0*
#38650
b110 %
b110 /
1*
#38700
0*
#38750
b111 %
b111 /
1*
#38800
0*
#38850
b1000 %
b1000 /
1*
#38900
0*
#38950
1$
b1001 %
b1001 /
1*
#39000
0*
#39050
0$
b11 #
b11 0
b0 %
b0 /
1*
#39100
0*
#39150
b1 %
b1 /
1*
#39200
0*
#39250
b10 %
b10 /
1*
#39300
0*
#39350
b11 %
b11 /
1*
#39400
0*
#39450
b100 %
b100 /
1*
#39500
0*
#39550
b101 %
b101 /
1*
#39600
0*
#39650
b110 %
b110 /
1*
#39700
0*
#39750
b111 %
b111 /
1*
#39800
0*
#39850
b1000 %
b1000 /
1*
#39900
0*
#39950
1$
b1001 %
b1001 /
1*
#40000
0*
#40050
0$
b100 #
b100 0
b0 %
b0 /
1*
#40100
0*
#40150
b1 %
b1 /
1*
#40200
0*
#40250
b10 %
b10 /
1*
#40300
0*
#40350
b11 %
b11 /
1*
#40400
0*
#40450
b100 %
b100 /
1*
#40500
0*
#40550
b101 %
b101 /
1*
#40600
0*
#40650
b110 %
b110 /
1*
#40700
0*
#40750
b111 %
b111 /
1*
#40800
0*
#40850
b1000 %
b1000 /
1*
#40900
0*
#40950
1$
b1001 %
b1001 /
1*
#41000
0*
#41050
0$
b101 #
b101 0
b0 %
b0 /
1*
#41100
0*
#41150
b1 %
b1 /
1*
#41200
0*
#41250
b10 %
b10 /
1*
#41300
0*
#41350
b11 %
b11 /
1*
#41400
0*
#41450
b100 %
b100 /
1*
#41500
0*
#41550
b101 %
b101 /
1*
#41600
0*
#41650
b110 %
b110 /
1*
#41700
0*
#41750
b111 %
b111 /
1*
#41800
0*
#41850
b1000 %
b1000 /
1*
#41900
0*
#41950
1"
1$
b1001 %
b1001 /
1*
#42000
0*
#42050
0"
0$
b111 )
b111 -
b0 #
b0 0
b0 %
b0 /
1*
#42100
0*
#42150
b1 %
b1 /
1*
#42200
0*
#42250
b10 %
b10 /
1*
#42300
0*
#42350
b11 %
b11 /
1*
#42400
0*
#42450
b100 %
b100 /
1*
#42500
0*
#42550
b101 %
b101 /
1*
#42600
0*
#42650
b110 %
b110 /
1*
#42700
0*
#42750
b111 %
b111 /
1*
#42800
0*
#42850
b1000 %
b1000 /
1*
#42900
0*
#42950
1$
b1001 %
b1001 /
1*
#43000
0*
#43050
0$
b1 #
b1 0
b0 %
b0 /
1*
#43100
0*
#43150
b1 %
b1 /
1*
#43200
0*
#43250
b10 %
b10 /
1*
#43300
0*
#43350
b11 %
b11 /
1*
#43400
0*
#43450
b100 %
b100 /
1*
#43500
0*
#43550
b101 %
b101 /
1*
#43600
0*
#43650
b110 %
b110 /
1*
#43700
0*
#43750
b111 %
b111 /
1*
#43800
0*
#43850
b1000 %
b1000 /
1*
#43900
0*
#43950
1$
b1001 %
b1001 /
1*
#44000
0*
#44050
0$
b10 #
b10 0
b0 %
b0 /
1*
#44100
0*
#44150
b1 %
b1 /
1*
#44200
0*
#44250
b10 %
b10 /
1*
#44300
0*
#44350
b11 %
b11 /
1*
#44400
0*
#44450
b100 %
b100 /
1*
#44500
0*
#44550
b101 %
b101 /
1*
#44600
0*
#44650
b110 %
b110 /
1*
#44700
0*
#44750
b111 %
b111 /
1*
#44800
0*
#44850
b1000 %
b1000 /
1*
#44900
0*
#44950
1$
b1001 %
b1001 /
1*
#45000
0*
#45050
0$
b11 #
b11 0
b0 %
b0 /
1*
#45100
0*
#45150
b1 %
b1 /
1*
#45200
0*
#45250
b10 %
b10 /
1*
#45300
0*
#45350
b11 %
b11 /
1*
#45400
0*
#45450
b100 %
b100 /
1*
#45500
0*
#45550
b101 %
b101 /
1*
#45600
0*
#45650
b110 %
b110 /
1*
#45700
0*
#45750
b111 %
b111 /
1*
#45800
0*
#45850
b1000 %
b1000 /
1*
#45900
0*
#45950
1$
b1001 %
b1001 /
1*
#46000
0*
#46050
0$
b100 #
b100 0
b0 %
b0 /
1*
#46100
0*
#46150
b1 %
b1 /
1*
#46200
0*
#46250
b10 %
b10 /
1*
#46300
0*
#46350
b11 %
b11 /
1*
#46400
0*
#46450
b100 %
b100 /
1*
#46500
0*
#46550
b101 %
b101 /
1*
#46600
0*
#46650
b110 %
b110 /
1*
#46700
0*
#46750
b111 %
b111 /
1*
#46800
0*
#46850
b1000 %
b1000 /
1*
#46900
0*
#46950
1$
b1001 %
b1001 /
1*
#47000
0*
#47050
0$
b101 #
b101 0
b0 %
b0 /
1*
#47100
0*
#47150
b1 %
b1 /
1*
#47200
0*
#47250
b10 %
b10 /
1*
#47300
0*
#47350
b11 %
b11 /
1*
#47400
0*
#47450
b100 %
b100 /
1*
#47500
0*
#47550
b101 %
b101 /
1*
#47600
0*
#47650
b110 %
b110 /
1*
#47700
0*
#47750
b111 %
b111 /
1*
#47800
0*
#47850
b1000 %
b1000 /
1*
#47900
0*
#47950
1"
1$
b1001 %
b1001 /
1*
#48000
0*
#48050
0"
0$
b1000 )
b1000 -
b0 #
b0 0
b0 %
b0 /
1*
#48100
0*
#48150
b1 %
b1 /
1*
#48200
0*
#48250
b10 %
b10 /
1*
#48300
0*
#48350
b11 %
b11 /
1*
#48400
0*
#48450
b100 %
b100 /
1*
#48500
0*
#48550
b101 %
b101 /
1*
#48600
0*
#48650
b110 %
b110 /
1*
#48700
0*
#48750
b111 %
b111 /
1*
#48800
0*
#48850
b1000 %
b1000 /
1*
#48900
0*
#48950
1$
b1001 %
b1001 /
1*
#49000
0*
#49050
0$
b1 #
b1 0
b0 %
b0 /
1*
#49100
0*
#49150
b1 %
b1 /
1*
#49200
0*
#49250
b10 %
b10 /
1*
#49300
0*
#49350
b11 %
b11 /
1*
#49400
0*
#49450
b100 %
b100 /
1*
#49500
0*
#49550
b101 %
b101 /
1*
#49600
0*
#49650
b110 %
b110 /
1*
#49700
0*
#49750
b111 %
b111 /
1*
#49800
0*
#49850
b1000 %
b1000 /
1*
#49900
0*
#49950
1$
b1001 %
b1001 /
1*
#50000
0*
