Digital-Circuit-Design/MP2/SeqRcgn.v
`timescale 1ns/10ps
module SeqRcgn (out,x,clk,reset_) ;
// Port declarations
output out ;
input x,clk,reset_ ;

reg out ;
reg[2:0] state, next_state ;

parameter A= 3'b000, B=3'b001, C=3'b011, D=3'b010, E=3'b110;

always@ (posedge clk or negedge reset_)
	if(!reset_)	// an asynchronous reset_
		state = A ;
	else
		state = next_state ;

always@ (state or x)
    case(state)		// state transition
    A:
		if(x)
			next_state = A ;
		else
			next_state = B ;
	B:
		if(x)
			next_state = A ;
		else
			next_state = C ;
	C:
		if(x)
			next_state = D ;
		else
			next_state = C ;
	D:
		if(x)
			next_state = A ;
		else
			next_state = E ;
	E:
		if(x)
			next_state = A ;
		else
			next_state = C ;
	default:
		next_state = 3'bxxx ;
	endcase

always@ (state)
	case (state)
	A, B, C, D:
		out = 0 ;
	E:
		out = 1 ;
	default:
		out = 1'bx ;
	endcase

endmodule

module test_SeqRcng ;

reg x, clk, reset_ ;

//SeqRcgn instance
    SeqRcgn SR1 (out, x, clk, reset_) ;

//Stimulus
initial
begin
	clk = 1'b0 ;
	repeat(30)
		#10 clk = ~clk ;
end

initial
begin
  x = 0 ; reset_ = 0;
  #15  reset_ = 1; x = 1 ;
  #20  x = 0 ;
  #20  x = 1 ;
  #20  x = 0 ;
  #20  x = 0 ;
  #20  x = 1 ;
  #20  x = 0 ;
  #20  x = 0 ;
  #20  x = 1 ;
  #20  x = 0 ;
  #20  x = 0 ;
  #20  x = 1 ;
  #20  x = 1 ;
  #20  x = 1 ;
  #20  x = 0 ;
  #20  x = 1 ;

end

//Display results
initial
begin
  $display("                time out  x   clk  reset_");
  $monitor($time, "  %b   %b   %b   %b", out, x, clk, reset_) ;
end

initial
begin
$dumpfile("SeqRcgn.vcd");
$dumpvars;
end

endmodule

Digital-Circuit-Design/MP2/SeqRcgn.vcd
$date
	Mon May 28 23:15:22 2018
$end
$version
	Icarus Verilog
$end
$timescale
	10ps
$end
$scope module test_SeqRcng $end
$var wire 1 ! out $end
$var reg 1 " clk $end
$var reg 1 # reset_ $end
$var reg 1 $ x $end
$scope module SR1 $end
$var wire 1 " clk $end
$var wire 1 # reset_ $end
$var wire 1 $ x $end
$var reg 3 % next_state [2:0] $end
$var reg 1 ! out $end
$var reg 3 & state [2:0] $end
$upscope $end
$upscope $end
$enddefinitions $end
#0
$dumpvars
b0 &
b1 %
0$
0#
0"
0!
$end
#1000
1"
#1500
b0 %
1$
1#
#2000
0"
#3000
1"
#3500
b1 %
0$
#4000
0"
#5000
b11 %
b1 &
1"
#5500
b0 %
1$
#6000
0"
#7000
b0 &
1"
#7500
b1 %
0$
#8000
0"
#9000
b11 %
b1 &
1"
#10000
0"
#11000
b11 &
1"
#11500
b10 %
1$
#12000
0"
#13000
b0 %
b10 &
1"
#13500
b110 %
0$
#14000
0"
#15000
1!
b11 %
b110 &
1"
#16000
0"
#17000
0!
b11 &
1"
#17500
b10 %
1$
#18000
0"
#19000
b0 %
b10 &
1"
#19500
b110 %
0$
#20000
0"
#21000
1!
b11 %
b110 &
1"
#22000
0"
#23000
0!
b11 &
1"
#23500
b10 %
1$
#24000
0"
#25000
b0 %
b10 &
1"
#26000
0"
#27000
b0 &
1"
#28000
0"
#29000
1"
#29500
b1 %
0$
#30000
0"
#31500
b0 %
1$
